{
   "propertyInfo" : [
      {
         "access" : "R",
         "changeMode" : "ON_CHANGE",
         "comment" : "int32Values[0] :EPBSts\nint32Values[1] :EPBErrSts",
         "propertyName" : "GWM_EPBSts",
         "propertyType" : "INT32_VEC",
         "signal" : [
            {
               "firstCoding" : "0x0:Released\n0x1:Closed\n0x2:In progress\n0x3:Unknown",
               "isProjectExit" : {
                  "A07\u0402\u011c\u0534" : true,
                  "A07\u052b\u0373\u05af\ufffd" : true,
                  "A08\u0402\u011c\u0534" : true,
                  "A08\u052b\u0373\u05af\ufffd" : true,
                  "B02\u0402\u011c\u0534" : true,
                  "B02\u052b\u0373\u05af\ufffd" : true,
                  "B03" : true,
                  "B07/B16(\u067a\u011a&\u06a3\u0362\u00e9" : true,
                  "D01/D02/D03\u0402\u011c\u0534" : true,
                  "D01/D02/D03\u052b\u0373\u05af\ufffd" : true,
                  "D02\u06a3\u0362P0" : true,
                  "D02\u06a3\u0362P2" : true,
                  "EC24" : true,
                  "EC24\u06a3\u0362" : true,
                  "EC31" : true,
                  "ES13" : true,
                  "ES24" : true,
                  "P01\u06a3\u0362HEV\u05af\ufffd" : true,
                  "P01\u06a3\u0362\u052b\u0373\u05af\ufffd" : true,
                  "P02\u0402\u011c\u0534" : true,
                  "P02\u052b\u0373\u05af\ufffd" : true,
                  "P02\u06a3\u0362\u0402\u011c\u0534" : true,
                  "P02\u06a3\u0362\u052b\u0373\u05af\ufffd" : true,
                  "P03\u0402\u011c\u0534" : true,
                  "P03\u052b\u0373\u05af\ufffd" : true,
                  "P03\u06a3\u0362\u0402\u011c\u0534" : true,
                  "P03\u06a3\u0362\u052b\u0373\u05af\ufffd" : true,
                  "P05PHEV6*6" : true,
                  "P05\u0402\u011c\u0534" : true,
                  "P05\u052b\u0373\u05af\ufffd" : true,
                  "P05\u06a3\u0362HEV" : true,
                  "P05\u06a3\u0362\u052b\u0373\u05af\ufffd" : true,
                  "P09 EV" : true,
                  "P09\u0402\u011c\u0534" : true,
                  "P09\u052b\u0373\u05af\ufffd" : true,
                  "P11" : true
               },
               "messagName" : "EPB1",
               "messageID" : "0x16B",
               "secondCoding" : "0x0:Released\n0x1:Closed\n0x2:In progress\n0x3:unknown",
               "signaleName" : "EPBSts"
            },
            {
               "firstCoding" : "0x0:Released\n0x1:Closed\n0x2:In progress\n0x3:unknown",
               "isProjectExit" : {
                  "A07\u0402\u011c\u0534" : false,
                  "A07\u052b\u0373\u05af\ufffd" : false,
                  "A08\u0402\u011c\u0534" : false,
                  "A08\u052b\u0373\u05af\ufffd" : false,
                  "B02\u0402\u011c\u0534" : false,
                  "B02\u052b\u0373\u05af\ufffd" : false,
                  "B03" : false,
                  "B07/B16(\u067a\u011a&\u06a3\u0362\u00e9" : false,
                  "D01/D02/D03\u0402\u011c\u0534" : false,
                  "D01/D02/D03\u052b\u0373\u05af\ufffd" : false,
                  "D02\u06a3\u0362P0" : false,
                  "D02\u06a3\u0362P2" : false,
                  "EC24" : false,
                  "EC24\u06a3\u0362" : false,
                  "EC31" : false,
                  "ES13" : false,
                  "ES24" : false,
                  "P01\u06a3\u0362HEV\u05af\ufffd" : false,
                  "P01\u06a3\u0362\u052b\u0373\u05af\ufffd" : false,
                  "P02\u0402\u011c\u0534" : false,
                  "P02\u052b\u0373\u05af\ufffd" : false,
                  "P02\u06a3\u0362\u0402\u011c\u0534" : false,
                  "P02\u06a3\u0362\u052b\u0373\u05af\ufffd" : false,
                  "P03\u0402\u011c\u0534" : false,
                  "P03\u052b\u0373\u05af\ufffd" : false,
                  "P03\u06a3\u0362\u0402\u011c\u0534" : false,
                  "P03\u06a3\u0362\u052b\u0373\u05af\ufffd" : false,
                  "P05PHEV6*6" : false,
                  "P05\u0402\u011c\u0534" : false,
                  "P05\u052b\u0373\u05af\ufffd" : false,
                  "P05\u06a3\u0362HEV" : false,
                  "P05\u06a3\u0362\u052b\u0373\u05af\ufffd" : false,
                  "P09 EV" : false,
                  "P09\u0402\u011c\u0534" : false,
                  "P09\u052b\u0373\u05af\ufffd" : false,
                  "P11" : false
               },
               "messagName" : "ESP_FD3",
               "messageID" : "0x13B",
               "secondCoding" : "0x0:Released\n0x1:Closed\n0x2:In progress\n0x3:unknown",
               "signaleName" : "EPBSts"
            },
            {
               "firstCoding" : "0x0:Undefined\n0x1:No Error\n0x2:Error\n0x3:Diagnosis",
               "isProjectExit" : {
                  "A07\u0402\u011c\u0534" : true,
                  "A07\u052b\u0373\u05af\ufffd" : true,
                  "A08\u0402\u011c\u0534" : true,
                  "A08\u052b\u0373\u05af\ufffd" : true,
                  "B02\u0402\u011c\u0534" : true,
                  "B02\u052b\u0373\u05af\ufffd" : true,
                  "B03" : true,
                  "B07/B16(\u067a\u011a&\u06a3\u0362\u00e9" : true,
                  "D01/D02/D03\u0402\u011c\u0534" : true,
                  "D01/D02/D03\u052b\u0373\u05af\ufffd" : true,
                  "D02\u06a3\u0362P0" : true,
                  "D02\u06a3\u0362P2" : true,
                  "EC24" : true,
                  "EC24\u06a3\u0362" : true,
                  "EC31" : true,
                  "ES13" : true,
                  "ES24" : true,
                  "P01\u06a3\u0362HEV\u05af\ufffd" : true,
                  "P01\u06a3\u0362\u052b\u0373\u05af\ufffd" : true,
                  "P02\u0402\u011c\u0534" : true,
                  "P02\u052b\u0373\u05af\ufffd" : true,
                  "P02\u06a3\u0362\u0402\u011c\u0534" : true,
                  "P02\u06a3\u0362\u052b\u0373\u05af\ufffd" : true,
                  "P03\u0402\u011c\u0534" : true,
                  "P03\u052b\u0373\u05af\ufffd" : true,
                  "P03\u06a3\u0362\u0402\u011c\u0534" : true,
                  "P03\u06a3\u0362\u052b\u0373\u05af\ufffd" : true,
                  "P05PHEV6*6" : true,
                  "P05\u0402\u011c\u0534" : true,
                  "P05\u052b\u0373\u05af\ufffd" : true,
                  "P05\u06a3\u0362HEV" : true,
                  "P05\u06a3\u0362\u052b\u0373\u05af\ufffd" : true,
                  "P09 EV" : true,
                  "P09\u0402\u011c\u0534" : true,
                  "P09\u052b\u0373\u05af\ufffd" : true,
                  "P11" : true
               },
               "messagName" : "EPB1",
               "messageID" : "0x16B",
               "secondCoding" : "0x0:Undefined\n0x1:No Error\n0x2:Error\n0x3:Diagnosis",
               "signaleName" : "EPBErrSts"
            },
            {
               "firstCoding" : "0x0:Undefined\n0x1:No Error\n0x2:Error\n0x3:Diagnosis",
               "isProjectExit" : {
                  "A07\u0402\u011c\u0534" : false,
                  "A07\u052b\u0373\u05af\ufffd" : false,
                  "A08\u0402\u011c\u0534" : false,
                  "A08\u052b\u0373\u05af\ufffd" : false,
                  "B02\u0402\u011c\u0534" : false,
                  "B02\u052b\u0373\u05af\ufffd" : false,
                  "B03" : false,
                  "B07/B16(\u067a\u011a&\u06a3\u0362\u00e9" : false,
                  "D01/D02/D03\u0402\u011c\u0534" : false,
                  "D01/D02/D03\u052b\u0373\u05af\ufffd" : false,
                  "D02\u06a3\u0362P0" : false,
                  "D02\u06a3\u0362P2" : false,
                  "EC24" : false,
                  "EC24\u06a3\u0362" : false,
                  "EC31" : false,
                  "ES13" : false,
                  "ES24" : false,
                  "P01\u06a3\u0362HEV\u05af\ufffd" : false,
                  "P01\u06a3\u0362\u052b\u0373\u05af\ufffd" : false,
                  "P02\u0402\u011c\u0534" : false,
                  "P02\u052b\u0373\u05af\ufffd" : false,
                  "P02\u06a3\u0362\u0402\u011c\u0534" : false,
                  "P02\u06a3\u0362\u052b\u0373\u05af\ufffd" : false,
                  "P03\u0402\u011c\u0534" : false,
                  "P03\u052b\u0373\u05af\ufffd" : false,
                  "P03\u06a3\u0362\u0402\u011c\u0534" : false,
                  "P03\u06a3\u0362\u052b\u0373\u05af\ufffd" : false,
                  "P05PHEV6*6" : false,
                  "P05\u0402\u011c\u0534" : false,
                  "P05\u052b\u0373\u05af\ufffd" : false,
                  "P05\u06a3\u0362HEV" : false,
                  "P05\u06a3\u0362\u052b\u0373\u05af\ufffd" : false,
                  "P09 EV" : false,
                  "P09\u0402\u011c\u0534" : false,
                  "P09\u052b\u0373\u05af\ufffd" : false,
                  "P11" : false
               },
               "messagName" : "ESP_FD3",
               "messageID" : "0x13B",
               "secondCoding" : "0x0:Undefined\n0x1:No Error\n0x2:Error\n0x3:Diagnosis",
               "signaleName" : "EPBErrSts"
            }
         ]
      },
      {
         "access" : "R",
         "changeMode" : "CONTINUOUS",
         "comment" : " floatValues[0] :EngSpd\n floatValues[1] :EngSpdVld\n\u0562\u07e9\u0266\u0730\ufffd\u04bf\u05d6\u009f\u072d\u00fa\n1\u00ec\u04bb\u0538\u06b3\u05fa\u068d_PHEV\u06b3\u05fa\u0544\u0405\u0685\u0544\u068f\u04a2\n2\u00ecEngSpd \u068d EngSpdVld\u0544\u05e9\u068f\u024f\u0468",
         "propertyName" : "GWM_EngSpd",
         "propertyType" : "FLOAT_VEC",
         "signal" : [
            {
               "firstCoding" : "0x0000-0xFFFF:Valid values",
               "isProjectExit" : {
                  "A07\u0402\u011c\u0534" : true,
                  "A07\u052b\u0373\u05af\ufffd" : true,
                  "A08\u0402\u011c\u0534" : true,
                  "A08\u052b\u0373\u05af\ufffd" : true,
                  "B02\u0402\u011c\u0534" : true,
                  "B02\u052b\u0373\u05af\ufffd" : true,
                  "B03" : true,
                  "B07/B16(\u067a\u011a&\u06a3\u0362\u00e9" : false,
                  "D01/D02/D03\u0402\u011c\u0534" : false,
                  "D01/D02/D03\u052b\u0373\u05af\ufffd" : true,
                  "D02\u06a3\u0362P0" : false,
                  "D02\u06a3\u0362P2" : false,
                  "EC24" : false,
                  "EC24\u06a3\u0362" : false,
                  "EC31" : false,
                  "ES13" : false,
                  "ES24" : false,
                  "P01\u06a3\u0362HEV\u05af\ufffd" : false,
                  "P01\u06a3\u0362\u052b\u0373\u05af\ufffd" : false,
                  "P02\u0402\u011c\u0534" : false,
                  "P02\u052b\u0373\u05af\ufffd" : true,
                  "P02\u06a3\u0362\u0402\u011c\u0534" : false,
                  "P02\u06a3\u0362\u052b\u0373\u05af\ufffd" : true,
                  "P03\u0402\u011c\u0534" : false,
                  "P03\u052b\u0373\u05af\ufffd" : true,
                  "P03\u06a3\u0362\u0402\u011c\u0534" : false,
                  "P03\u06a3\u0362\u052b\u0373\u05af\ufffd" : true,
                  "P05PHEV6*6" : false,
                  "P05\u0402\u011c\u0534" : false,
                  "P05\u052b\u0373\u05af\ufffd" : true,
                  "P05\u06a3\u0362HEV" : false,
                  "P05\u06a3\u0362\u052b\u0373\u05af\ufffd" : true,
                  "P09 EV" : false,
                  "P09\u0402\u011c\u0534" : false,
                  "P09\u052b\u0373\u05af\ufffd" : false,
                  "P11" : false
               },
               "messagName" : "ECM1",
               "messageID" : "0x111",
               "secondCoding" : "0x0000- 0xFFFF:Valid values ",
               "signaleName" : "EngSpd"
            },
            {
               "firstCoding" : "0x0:Invalid\n0x1:Valid\n0x2:Initial value\n0x3:Reserved",
               "isProjectExit" : {
                  "A07\u0402\u011c\u0534" : true,
                  "A07\u052b\u0373\u05af\ufffd" : true,
                  "A08\u0402\u011c\u0534" : true,
                  "A08\u052b\u0373\u05af\ufffd" : true,
                  "B02\u0402\u011c\u0534" : true,
                  "B02\u052b\u0373\u05af\ufffd" : true,
                  "B03" : true,
                  "B07/B16(\u067a\u011a&\u06a3\u0362\u00e9" : true,
                  "D01/D02/D03\u0402\u011c\u0534" : false,
                  "D01/D02/D03\u052b\u0373\u05af\ufffd" : true,
                  "D02\u06a3\u0362P0" : true,
                  "D02\u06a3\u0362P2" : false,
                  "EC24" : false,
                  "EC24\u06a3\u0362" : false,
                  "EC31" : false,
                  "ES13" : false,
                  "ES24" : false,
                  "P01\u06a3\u0362HEV\u05af\ufffd" : false,
                  "P01\u06a3\u0362\u052b\u0373\u05af\ufffd" : true,
                  "P02\u0402\u011c\u0534" : false,
                  "P02\u052b\u0373\u05af\ufffd" : true,
                  "P02\u06a3\u0362\u0402\u011c\u0534" : false,
                  "P02\u06a3\u0362\u052b\u0373\u05af\ufffd" : true,
                  "P03\u0402\u011c\u0534" : false,
                  "P03\u052b\u0373\u05af\ufffd" : true,
                  "P03\u06a3\u0362\u0402\u011c\u0534" : false,
                  "P03\u06a3\u0362\u052b\u0373\u05af\ufffd" : true,
                  "P05PHEV6*6" : false,
                  "P05\u0402\u011c\u0534" : false,
                  "P05\u052b\u0373\u05af\ufffd" : true,
                  "P05\u06a3\u0362HEV" : false,
                  "P05\u06a3\u0362\u052b\u0373\u05af\ufffd" : true,
                  "P09 EV" : false,
                  "P09\u0402\u011c\u0534" : false,
                  "P09\u052b\u0373\u05af\ufffd" : true,
                  "P11" : true
               },
               "messagName" : "ECM1",
               "messageID" : "0x111",
               "secondCoding" : "0x0000- 0xFFFF:Valid values ",
               "signaleName" : "EngSpdVldty"
            },
            {
               "firstCoding" : "0x0000- 0xFFFF:Valid values ",
               "isProjectExit" : {
                  "A07\u0402\u011c\u0534" : false,
                  "A07\u052b\u0373\u05af\ufffd" : false,
                  "A08\u0402\u011c\u0534" : false,
                  "A08\u052b\u0373\u05af\ufffd" : false,
                  "B02\u0402\u011c\u0534" : false,
                  "B02\u052b\u0373\u05af\ufffd" : false,
                  "B03" : false,
                  "B07/B16(\u067a\u011a&\u06a3\u0362\u00e9" : false,
                  "D01/D02/D03\u0402\u011c\u0534" : true,
                  "D01/D02/D03\u052b\u0373\u05af\ufffd" : false,
                  "D02\u06a3\u0362P0" : false,
                  "D02\u06a3\u0362P2" : true,
                  "EC24" : false,
                  "EC24\u06a3\u0362" : false,
                  "EC31" : false,
                  "ES13" : false,
                  "ES24" : false,
                  "P01\u06a3\u0362HEV\u05af\ufffd" : true,
                  "P01\u06a3\u0362\u052b\u0373\u05af\ufffd" : false,
                  "P02\u0402\u011c\u0534" : true,
                  "P02\u052b\u0373\u05af\ufffd" : false,
                  "P02\u06a3\u0362\u0402\u011c\u0534" : true,
                  "P02\u06a3\u0362\u052b\u0373\u05af\ufffd" : false,
                  "P03\u0402\u011c\u0534" : true,
                  "P03\u052b\u0373\u05af\ufffd" : false,
                  "P03\u06a3\u0362\u0402\u011c\u0534" : true,
                  "P03\u06a3\u0362\u052b\u0373\u05af\ufffd" : false,
                  "P05PHEV6*6" : true,
                  "P05\u0402\u011c\u0534" : true,
                  "P05\u052b\u0373\u05af\ufffd" : false,
                  "P05\u06a3\u0362HEV" : true,
                  "P05\u06a3\u0362\u052b\u0373\u05af\ufffd" : false,
                  "P09 EV" : false,
                  "P09\u0402\u011c\u0534" : true,
                  "P09\u052b\u0373\u05af\ufffd" : false,
                  "P11" : false
               },
               "messagName" : "ECM1",
               "messageID" : "0x111",
               "secondCoding" : "0x0:Invalid\n0x1:Valid\n0x2:Initial value\n0x3:Reserved",
               "signaleName" : "EngSpd_PHEV"
            },
            {
               "firstCoding" : "0x0:Invalid\n0x1:Valid\n0x2:Initial value\n0x3:Reserved",
               "isProjectExit" : {
                  "A07\u0402\u011c\u0534" : false,
                  "A07\u052b\u0373\u05af\ufffd" : false,
                  "A08\u0402\u011c\u0534" : false,
                  "A08\u052b\u0373\u05af\ufffd" : false,
                  "B02\u0402\u011c\u0534" : false,
                  "B02\u052b\u0373\u05af\ufffd" : false,
                  "B03" : false,
                  "B07/B16(\u067a\u011a&\u06a3\u0362\u00e9" : false,
                  "D01/D02/D03\u0402\u011c\u0534" : true,
                  "D01/D02/D03\u052b\u0373\u05af\ufffd" : false,
                  "D02\u06a3\u0362P0" : false,
                  "D02\u06a3\u0362P2" : true,
                  "EC24" : false,
                  "EC24\u06a3\u0362" : false,
                  "EC31" : false,
                  "ES13" : false,
                  "ES24" : false,
                  "P01\u06a3\u0362HEV\u05af\ufffd" : true,
                  "P01\u06a3\u0362\u052b\u0373\u05af\ufffd" : false,
                  "P02\u0402\u011c\u0534" : true,
                  "P02\u052b\u0373\u05af\ufffd" : false,
                  "P02\u06a3\u0362\u0402\u011c\u0534" : true,
                  "P02\u06a3\u0362\u052b\u0373\u05af\ufffd" : false,
                  "P03\u0402\u011c\u0534" : true,
                  "P03\u052b\u0373\u05af\ufffd" : false,
                  "P03\u06a3\u0362\u0402\u011c\u0534" : true,
                  "P03\u06a3\u0362\u052b\u0373\u05af\ufffd" : false,
                  "P05PHEV6*6" : false,
                  "P05\u0402\u011c\u0534" : false,
                  "P05\u052b\u0373\u05af\ufffd" : false,
                  "P05\u06a3\u0362HEV" : false,
                  "P05\u06a3\u0362\u052b\u0373\u05af\ufffd" : false,
                  "P09 EV" : false,
                  "P09\u0402\u011c\u0534" : true,
                  "P09\u052b\u0373\u05af\ufffd" : false,
                  "P11" : false
               },
               "messagName" : "ECM1",
               "messageID" : "0x111",
               "secondCoding" : "0x0:Invalid\n0x1:Valid\n0x2:Initial value\n0x3:Reserved",
               "signaleName" : "EngSpdVldty_PHEV"
            }
         ]
      },
      {
         "access" : "R",
         "changeMode" : "ON_CHANGE",
         "comment" : "int32Values[0]: SysPowerMod\nint32Values[1]: SysPowerModVld",
         "propertyName" : "GWM_SysPowerMod",
         "propertyType" : "INT32_VEC",
         "signal" : [
            {
               "firstCoding" : "0x0:OFF\n0x1:ACC (reserved)\n0x2:ON\n0x3:Crank",
               "isProjectExit" : {
                  "A07\u0402\u011c\u0534" : true,
                  "A07\u052b\u0373\u05af\ufffd" : true,
                  "A08\u0402\u011c\u0534" : true,
                  "A08\u052b\u0373\u05af\ufffd" : true,
                  "B02\u0402\u011c\u0534" : true,
                  "B02\u052b\u0373\u05af\ufffd" : true,
                  "B03" : true,
                  "B07/B16(\u067a\u011a&\u06a3\u0362\u00e9" : true,
                  "D01/D02/D03\u0402\u011c\u0534" : true,
                  "D01/D02/D03\u052b\u0373\u05af\ufffd" : true,
                  "D02\u06a3\u0362P0" : true,
                  "D02\u06a3\u0362P2" : true,
                  "EC24" : true,
                  "EC24\u06a3\u0362" : true,
                  "EC31" : true,
                  "ES13" : true,
                  "ES24" : true,
                  "P01\u06a3\u0362HEV\u05af\ufffd" : true,
                  "P01\u06a3\u0362\u052b\u0373\u05af\ufffd" : true,
                  "P02\u0402\u011c\u0534" : true,
                  "P02\u052b\u0373\u05af\ufffd" : true,
                  "P02\u06a3\u0362\u0402\u011c\u0534" : true,
                  "P02\u06a3\u0362\u052b\u0373\u05af\ufffd" : true,
                  "P03\u0402\u011c\u0534" : true,
                  "P03\u052b\u0373\u05af\ufffd" : true,
                  "P03\u06a3\u0362\u0402\u011c\u0534" : true,
                  "P03\u06a3\u0362\u052b\u0373\u05af\ufffd" : true,
                  "P05PHEV6*6" : true,
                  "P05\u0402\u011c\u0534" : true,
                  "P05\u052b\u0373\u05af\ufffd" : true,
                  "P05\u06a3\u0362HEV" : true,
                  "P05\u06a3\u0362\u052b\u0373\u05af\ufffd" : true,
                  "P09 EV" : true,
                  "P09\u0402\u011c\u0534" : true,
                  "P09\u052b\u0373\u05af\ufffd" : true,
                  "P11" : true
               },
               "messagName" : "PEPS2",
               "messageID" : "0x295",
               "secondCoding" : "0x0:OFF\n0x1:ACC (reserved)\n0x2:ON\n0x3:Crank",
               "signaleName" : "SysPowerMod"
            },
            {
               "firstCoding" : "0x0:Invalid\n0x1:Valid",
               "isProjectExit" : {
                  "A07\u0402\u011c\u0534" : true,
                  "A07\u052b\u0373\u05af\ufffd" : true,
                  "A08\u0402\u011c\u0534" : true,
                  "A08\u052b\u0373\u05af\ufffd" : true,
                  "B02\u0402\u011c\u0534" : true,
                  "B02\u052b\u0373\u05af\ufffd" : true,
                  "B03" : true,
                  "B07/B16(\u067a\u011a&\u06a3\u0362\u00e9" : true,
                  "D01/D02/D03\u0402\u011c\u0534" : true,
                  "D01/D02/D03\u052b\u0373\u05af\ufffd" : true,
                  "D02\u06a3\u0362P0" : true,
                  "D02\u06a3\u0362P2" : true,
                  "EC24" : true,
                  "EC24\u06a3\u0362" : true,
                  "EC31" : true,
                  "ES13" : true,
                  "ES24" : true,
                  "P01\u06a3\u0362HEV\u05af\ufffd" : true,
                  "P01\u06a3\u0362\u052b\u0373\u05af\ufffd" : true,
                  "P02\u0402\u011c\u0534" : true,
                  "P02\u052b\u0373\u05af\ufffd" : true,
                  "P02\u06a3\u0362\u0402\u011c\u0534" : true,
                  "P02\u06a3\u0362\u052b\u0373\u05af\ufffd" : true,
                  "P03\u0402\u011c\u0534" : true,
                  "P03\u052b\u0373\u05af\ufffd" : true,
                  "P03\u06a3\u0362\u0402\u011c\u0534" : true,
                  "P03\u06a3\u0362\u052b\u0373\u05af\ufffd" : true,
                  "P05PHEV6*6" : true,
                  "P05\u0402\u011c\u0534" : true,
                  "P05\u052b\u0373\u05af\ufffd" : true,
                  "P05\u06a3\u0362HEV" : true,
                  "P05\u06a3\u0362\u052b\u0373\u05af\ufffd" : true,
                  "P09 EV" : true,
                  "P09\u0402\u011c\u0534" : true,
                  "P09\u052b\u0373\u05af\ufffd" : true,
                  "P11" : true
               },
               "messagName" : "PEPS2",
               "messageID" : "0x295",
               "secondCoding" : "0x0:Invalid\n0x1:Valid",
               "signaleName" : "SysPowerModVld"
            }
         ]
      },
      {
         "access" : "R",
         "changeMode" : "CONTINUOUS",
         "comment" : " floatValues[0] :VehSpd\n floatValues[1] :VehSpdVld",
         "propertyName" : "GWM_VehSpd",
         "propertyType" : "FLOAT_VEC",
         "signal" : [
            {
               "firstCoding" : "0x0000-0x14D5:Valid values\n0x14D6-0x1FFF:Reserved",
               "isProjectExit" : {
                  "A07\u0402\u011c\u0534" : false,
                  "A07\u052b\u0373\u05af\ufffd" : true,
                  "A08\u0402\u011c\u0534" : false,
                  "A08\u052b\u0373\u05af\ufffd" : true,
                  "B02\u0402\u011c\u0534" : true,
                  "B02\u052b\u0373\u05af\ufffd" : false,
                  "B03" : false,
                  "B07/B16(\u067a\u011a&\u06a3\u0362\u00e9" : false,
                  "D01/D02/D03\u0402\u011c\u0534" : false,
                  "D01/D02/D03\u052b\u0373\u05af\ufffd" : false,
                  "D02\u06a3\u0362P0" : false,
                  "D02\u06a3\u0362P2" : false,
                  "EC24" : false,
                  "EC24\u06a3\u0362" : false,
                  "EC31" : false,
                  "ES13" : false,
                  "ES24" : false,
                  "P01\u06a3\u0362HEV\u05af\ufffd" : false,
                  "P01\u06a3\u0362\u052b\u0373\u05af\ufffd" : false,
                  "P02\u0402\u011c\u0534" : false,
                  "P02\u052b\u0373\u05af\ufffd" : false,
                  "P02\u06a3\u0362\u0402\u011c\u0534" : false,
                  "P02\u06a3\u0362\u052b\u0373\u05af\ufffd" : false,
                  "P03\u0402\u011c\u0534" : false,
                  "P03\u052b\u0373\u05af\ufffd" : false,
                  "P03\u06a3\u0362\u0402\u011c\u0534" : false,
                  "P03\u06a3\u0362\u052b\u0373\u05af\ufffd" : false,
                  "P05PHEV6*6" : false,
                  "P05\u0402\u011c\u0534" : false,
                  "P05\u052b\u0373\u05af\ufffd" : true,
                  "P05\u06a3\u0362HEV" : false,
                  "P05\u06a3\u0362\u052b\u0373\u05af\ufffd" : true,
                  "P09 EV" : false,
                  "P09\u0402\u011c\u0534" : false,
                  "P09\u052b\u0373\u05af\ufffd" : false,
                  "P11" : true
               },
               "messagName" : "ABS3",
               "messageID" : "0x265",
               "secondCoding" : "0x0000-0x14D5:Valid values\n0x14D6-0x1FFF:Reserved",
               "signaleName" : "VehSpd"
            },
            {
               "firstCoding" : "0x0000-0x14D5:Valid values\n0x14D6-0x1FFF:Reserved",
               "isProjectExit" : {
                  "A07\u0402\u011c\u0534" : true,
                  "A07\u052b\u0373\u05af\ufffd" : false,
                  "A08\u0402\u011c\u0534" : true,
                  "A08\u052b\u0373\u05af\ufffd" : false,
                  "B02\u0402\u011c\u0534" : true,
                  "B02\u052b\u0373\u05af\ufffd" : true,
                  "B03" : true,
                  "B07/B16(\u067a\u011a&\u06a3\u0362\u00e9" : true,
                  "D01/D02/D03\u0402\u011c\u0534" : true,
                  "D01/D02/D03\u052b\u0373\u05af\ufffd" : true,
                  "D02\u06a3\u0362P0" : true,
                  "D02\u06a3\u0362P2" : true,
                  "EC24" : true,
                  "EC24\u06a3\u0362" : true,
                  "EC31" : true,
                  "ES13" : false,
                  "ES24" : true,
                  "P01\u06a3\u0362HEV\u05af\ufffd" : true,
                  "P01\u06a3\u0362\u052b\u0373\u05af\ufffd" : true,
                  "P02\u0402\u011c\u0534" : true,
                  "P02\u052b\u0373\u05af\ufffd" : true,
                  "P02\u06a3\u0362\u0402\u011c\u0534" : true,
                  "P02\u06a3\u0362\u052b\u0373\u05af\ufffd" : true,
                  "P03\u0402\u011c\u0534" : true,
                  "P03\u052b\u0373\u05af\ufffd" : true,
                  "P03\u06a3\u0362\u0402\u011c\u0534" : true,
                  "P03\u06a3\u0362\u052b\u0373\u05af\ufffd" : true,
                  "P05PHEV6*6" : true,
                  "P05\u0402\u011c\u0534" : true,
                  "P05\u052b\u0373\u05af\ufffd" : true,
                  "P05\u06a3\u0362HEV" : true,
                  "P05\u06a3\u0362\u052b\u0373\u05af\ufffd" : true,
                  "P09 EV" : true,
                  "P09\u0402\u011c\u0534" : true,
                  "P09\u052b\u0373\u05af\ufffd" : true,
                  "P11" : true
               },
               "messagName" : "ESP_FD2",
               "messageID" : "0x137",
               "secondCoding" : "0x0000-0x14D5:Valid values\n0x14D6-0x1FFF:Reserved",
               "signaleName" : "VehSpd"
            },
            {
               "firstCoding" : "0x0:Invalid\n0x1:Valid",
               "isProjectExit" : {
                  "A07\u0402\u011c\u0534" : false,
                  "A07\u052b\u0373\u05af\ufffd" : true,
                  "A08\u0402\u011c\u0534" : false,
                  "A08\u052b\u0373\u05af\ufffd" : true,
                  "B02\u0402\u011c\u0534" : true,
                  "B02\u052b\u0373\u05af\ufffd" : false,
                  "B03" : false,
                  "B07/B16(\u067a\u011a&\u06a3\u0362\u00e9" : false,
                  "D01/D02/D03\u0402\u011c\u0534" : false,
                  "D01/D02/D03\u052b\u0373\u05af\ufffd" : false,
                  "D02\u06a3\u0362P0" : false,
                  "D02\u06a3\u0362P2" : false,
                  "EC24" : false,
                  "EC24\u06a3\u0362" : false,
                  "EC31" : false,
                  "ES13" : false,
                  "ES24" : false,
                  "P01\u06a3\u0362HEV\u05af\ufffd" : false,
                  "P01\u06a3\u0362\u052b\u0373\u05af\ufffd" : false,
                  "P02\u0402\u011c\u0534" : false,
                  "P02\u052b\u0373\u05af\ufffd" : false,
                  "P02\u06a3\u0362\u0402\u011c\u0534" : false,
                  "P02\u06a3\u0362\u052b\u0373\u05af\ufffd" : false,
                  "P03\u0402\u011c\u0534" : false,
                  "P03\u052b\u0373\u05af\ufffd" : false,
                  "P03\u06a3\u0362\u0402\u011c\u0534" : false,
                  "P03\u06a3\u0362\u052b\u0373\u05af\ufffd" : false,
                  "P05PHEV6*6" : false,
                  "P05\u0402\u011c\u0534" : false,
                  "P05\u052b\u0373\u05af\ufffd" : true,
                  "P05\u06a3\u0362HEV" : false,
                  "P05\u06a3\u0362\u052b\u0373\u05af\ufffd" : true,
                  "P09 EV" : false,
                  "P09\u0402\u011c\u0534" : false,
                  "P09\u052b\u0373\u05af\ufffd" : false,
                  "P11" : true
               },
               "messagName" : "ABS3",
               "messageID" : "0x265",
               "secondCoding" : "0x0:Invalid\n0x1:Valid",
               "signaleName" : "VehSpdVld"
            },
            {
               "firstCoding" : "0x0:Invalid\n0x1:Valid",
               "isProjectExit" : {
                  "A07\u0402\u011c\u0534" : false,
                  "A07\u052b\u0373\u05af\ufffd" : false,
                  "A08\u0402\u011c\u0534" : false,
                  "A08\u052b\u0373\u05af\ufffd" : false,
                  "B02\u0402\u011c\u0534" : true,
                  "B02\u052b\u0373\u05af\ufffd" : false,
                  "B03" : false,
                  "B07/B16(\u067a\u011a&\u06a3\u0362\u00e9" : false,
                  "D01/D02/D03\u0402\u011c\u0534" : true,
                  "D01/D02/D03\u052b\u0373\u05af\ufffd" : true,
                  "D02\u06a3\u0362P0" : true,
                  "D02\u06a3\u0362P2" : true,
                  "EC24" : true,
                  "EC24\u06a3\u0362" : true,
                  "EC31" : true,
                  "ES13" : true,
                  "ES24" : true,
                  "P01\u06a3\u0362HEV\u05af\ufffd" : true,
                  "P01\u06a3\u0362\u052b\u0373\u05af\ufffd" : true,
                  "P02\u0402\u011c\u0534" : true,
                  "P02\u052b\u0373\u05af\ufffd" : true,
                  "P02\u06a3\u0362\u0402\u011c\u0534" : true,
                  "P02\u06a3\u0362\u052b\u0373\u05af\ufffd" : true,
                  "P03\u0402\u011c\u0534" : true,
                  "P03\u052b\u0373\u05af\ufffd" : true,
                  "P03\u06a3\u0362\u0402\u011c\u0534" : true,
                  "P03\u06a3\u0362\u052b\u0373\u05af\ufffd" : true,
                  "P05PHEV6*6" : true,
                  "P05\u0402\u011c\u0534" : true,
                  "P05\u052b\u0373\u05af\ufffd" : true,
                  "P05\u06a3\u0362HEV" : true,
                  "P05\u06a3\u0362\u052b\u0373\u05af\ufffd" : true,
                  "P09 EV" : true,
                  "P09\u0402\u011c\u0534" : true,
                  "P09\u052b\u0373\u05af\ufffd" : true,
                  "P11" : true
               },
               "messagName" : "ESP_FD2",
               "messageID" : "0x137",
               "secondCoding" : "0x0:Invalid\n0x1:Valid",
               "signaleName" : "VehSpdVld"
            }
         ]
      }
   ]
}
